LICENSE
anormalratingsystem/__init__.py
anormalratingsystem/computation/__init__.py
anormalratingsystem/computation/ranking.py
anormalratingsystem/config/__init__.py
anormalratingsystem/config/constants.py
anormalratingsystem/integrations/__init__.py
anormalratingsystem/interface/__init__.py
anormalratingsystem/interface/command_line.py
anormalratingsystem/logs/__init__.py
anormalratingsystem/logs/setup_logging.py
anormalratingsystem/main.py
anormalratingsystem/py.typed
anormalratingsystem/utilities/__init__.py
anormalratingsystem/utilities/file_handling.py
anormalratingsystem-0.1.5.dist-info/LICENSE
anormalratingsystem-0.1.5.dist-info/METADATA
anormalratingsystem-0.1.5.dist-info/WHEEL
anormalratingsystem-0.1.5.dist-info/entry_points.txt
anormalratingsystem-0.1.5.dist-info/RECORD
