Metadata-Version: 2.1
Name: anormalratingsystem
Version: 0.1.5
Summary: Rate anything from a scale of 1-10 with simple comparisons! The end result is even normally distributed. Do you like A better than B?
Home-page: https://github.com/unkokaeru/anormalratingsystem
License: MIT
Author: William Fayers
Author-email: william@fayers.com
Requires-Python: >=3.10,<4.0
Classifier: License :: OSI Approved :: MIT License
Classifier: Programming Language :: Python :: 3
Classifier: Programming Language :: Python :: 3.10
Classifier: Programming Language :: Python :: 3.11
Classifier: Programming Language :: Python :: 3.12
Classifier: Programming Language :: Python :: 3.13
Requires-Dist: rich (>=13.7.1,<14.0.0)
Project-URL: Repository, https://github.com/unkokaeru/anormalratingsystem
